tiny_todo/__init__.py
tiny_todo/__main__.py
tiny_todo/lib.py
tiny_todo-1.0.2.dist-info/LICENSE
tiny_todo-1.0.2.dist-info/METADATA
tiny_todo-1.0.2.dist-info/WHEEL
tiny_todo-1.0.2.dist-info/top_level.txt
tiny_todo-1.0.2.dist-info/RECORD
