Metadata-Version: 2.1
Name: tiny_todo
Version: 1.0.2
Summary: Simple to-do list application
Author-email: n4n5 <its.just.n4n5@gmail.com>
License: MIT License
Project-URL: Homepage, https://github.com/its-just-nans/tiny-todo
Project-URL: Bug Tracker, https://github.com/its-just-nans/tiny-todo/issues
Keywords: todo,todolist,tiny_todo,to_do,list
Classifier: License :: OSI Approved :: MIT License
Classifier: Programming Language :: Python
Classifier: Programming Language :: Python :: 3
Requires-Python: >=3.6
License-File: LICENSE
